Hydro_create/__init__.py
Hydro_create/create.py
Hydro_create-2.2.0.dist-info/METADATA
Hydro_create-2.2.0.dist-info/WHEEL
Hydro_create-2.2.0.dist-info/top_level.txt
Hydro_create-2.2.0.dist-info/RECORD
